dbview/__init__.py
dbview/helpers.py
dbview/models.py
django_database_view-0.3.0.dist-info/LICENSE
django_database_view-0.3.0.dist-info/METADATA
django_database_view-0.3.0.dist-info/WHEEL
django_database_view-0.3.0.dist-info/top_level.txt
django_database_view-0.3.0.dist-info/RECORD
